.cvsignore
.project
CHANGES
README
TODO
setup.py
ccrdf/__init__.py
ccrdf/aaronrdf.py
ccrdf/ccrdf.py
ccrdf/rdfdict.py
ccrdf/rdfextract.py
ccrdf.egg-info/PKG-INFO
ccrdf.egg-info/SOURCES.txt
ccrdf.egg-info/dependency_links.txt
ccrdf.egg-info/entry_points.txt
ccrdf.egg-info/requires.txt
ccrdf.egg-info/top_level.txt
ccrdf.egg-info/zip-safe
